gptdb/__init__.py
gptdb/_version.py
gptdb/component.py
gptdb/_private/__init__.py
gptdb/_private/config.py
gptdb/_private/llm_metadata.py
gptdb/_private/pydantic.py
gptdb/agent/__init__.py
gptdb/agent/core/__init__.py
gptdb/agent/core/agent.py
gptdb/agent/core/agent_manage.py
gptdb/agent/core/base_agent.py
gptdb/agent/core/base_team.py
gptdb/agent/core/role.py
gptdb/agent/core/schema.py
gptdb/agent/core/user_proxy_agent.py
gptdb/agent/core/action/__init__.py
gptdb/agent/core/action/base.py
gptdb/agent/core/action/blank_action.py
gptdb/agent/core/memory/__init__.py
gptdb/agent/core/memory/agent_memory.py
gptdb/agent/core/memory/base.py
gptdb/agent/core/memory/hybrid.py
gptdb/agent/core/memory/llm.py
gptdb/agent/core/memory/long_term.py
gptdb/agent/core/memory/short_term.py
gptdb/agent/core/memory/gpts/__init__.py
gptdb/agent/core/memory/gpts/base.py
gptdb/agent/core/memory/gpts/default_gpts_memory.py
gptdb/agent/core/memory/gpts/gpts_memory.py
gptdb/agent/core/plan/__init__.py
gptdb/agent/core/plan/plan_action.py
gptdb/agent/core/plan/planner_agent.py
gptdb/agent/core/plan/team_auto_plan.py
gptdb/agent/core/plan/awel/__init__.py
gptdb/agent/core/plan/awel/agent_operator.py
gptdb/agent/core/plan/awel/agent_operator_resource.py
gptdb/agent/core/plan/awel/team_awel_layout.py
gptdb/agent/core/profile/__init__.py
gptdb/agent/core/profile/base.py
gptdb/agent/expand/Indicator_assistant_agent.py
gptdb/agent/expand/__init__.py
gptdb/agent/expand/code_assistant_agent.py
gptdb/agent/expand/dashboard_assistant_agent.py
gptdb/agent/expand/data_scientist_agent.py
gptdb/agent/expand/retrieve_summary_assistant_agent.py
gptdb/agent/expand/summary_assistant_agent.py
gptdb/agent/expand/tool_assistant_agent.py
gptdb/agent/expand/actions/__init__.py
gptdb/agent/expand/actions/chart_action.py
gptdb/agent/expand/actions/code_action.py
gptdb/agent/expand/actions/dashboard_action.py
gptdb/agent/expand/actions/indicator_action.py
gptdb/agent/expand/actions/tool_action.py
gptdb-0.5.9.dist-info/LICENSE
gptdb-0.5.9.dist-info/METADATA
gptdb-0.5.9.dist-info/WHEEL
gptdb-0.5.9.dist-info/entry_points.txt
gptdb-0.5.9.dist-info/top_level.txt
gptdb-0.5.9.dist-info/RECORD
