Metadata-Version: 2.1
Name: gptdb
Version: 0.5.9
Summary: GPT-DB is an experimental open-source project that uses localized GPT large models to interact with your data and environment. With this solution, you can be assured that there is no risk of data leakage, and your data is 100% private and secure.
Home-page: https://github.com/khulnasoft/GPT-DB
Author: khulnasoft
Author-email: info@khulnasoft.com
License: https://opensource.org/license/mit/
Requires-Python: >=3.10
License-File: LICENSE
Requires-Dist: aiohttp ==3.8.4
Requires-Dist: chardet ==5.1.0
Requires-Dist: importlib-resources ==5.12.0
Requires-Dist: python-dotenv ==1.0.0
Requires-Dist: cachetools
Requires-Dist: pydantic >=2.6.0
Requires-Dist: typeguard
Requires-Dist: snowflake-id
Requires-Dist: typing-inspect
Provides-Extra: agent
Requires-Dist: cachetools ; extra == 'agent'
Requires-Dist: tomlkit ; extra == 'agent'
Requires-Dist: chardet ==5.1.0 ; extra == 'agent'
Requires-Dist: typeguard ; extra == 'agent'
Requires-Dist: importlib-resources ==5.12.0 ; extra == 'agent'
Requires-Dist: psutil ==5.9.4 ; extra == 'agent'
Requires-Dist: numpy <2.0.0,>=1.21.0 ; extra == 'agent'
Requires-Dist: httpx ; extra == 'agent'
Requires-Dist: click ; extra == 'agent'
Requires-Dist: aiohttp ==3.8.4 ; extra == 'agent'
Requires-Dist: tenacity <=8.3.0 ; extra == 'agent'
Requires-Dist: pydantic >=2.6.0 ; extra == 'agent'
Requires-Dist: prettytable ; extra == 'agent'
Requires-Dist: rich ; extra == 'agent'
Requires-Dist: snowflake-id ; extra == 'agent'
Requires-Dist: typing-inspect ; extra == 'agent'
Requires-Dist: fastapi >=0.100.0 ; extra == 'agent'
Requires-Dist: colorama ==0.4.6 ; extra == 'agent'
Requires-Dist: python-dotenv ==1.0.0 ; extra == 'agent'
Requires-Dist: termcolor ; extra == 'agent'
Requires-Dist: pandas ==2.0.3 ; extra == 'agent'
Provides-Extra: all
Requires-Dist: vllm ; extra == 'all'
Requires-Dist: jinja2 ; extra == 'all'
Requires-Dist: rocksdict ; extra == 'all'
Requires-Dist: xlrd ==2.0.1 ; extra == 'all'
Requires-Dist: torchaudio ==2.2.1 ; extra == 'all'
Requires-Dist: pymysql ; extra == 'all'
Requires-Dist: psutil ==5.9.4 ; extra == 'all'
Requires-Dist: sentence-transformers ; extra == 'all'
Requires-Dist: sentencepiece ; extra == 'all'
Requires-Dist: httpx ; extra == 'all'
Requires-Dist: aiohttp ==3.8.4 ; extra == 'all'
Requires-Dist: dashscope ; extra == 'all'
Requires-Dist: prettytable ; extra == 'all'
Requires-Dist: gTTS ==2.3.1 ; extra == 'all'
Requires-Dist: snowflake-id ; extra == 'all'
Requires-Dist: pymssql ; extra == 'all'
Requires-Dist: torch ==2.2.1 ; extra == 'all'
Requires-Dist: thrift-sasl ; extra == 'all'
Requires-Dist: ollama ; extra == 'all'
Requires-Dist: llama-cpp-python ; extra == 'all'
Requires-Dist: pymilvus ; extra == 'all'
Requires-Dist: python-multipart ; extra == 'all'
Requires-Dist: tomlkit ; extra == 'all'
Requires-Dist: coloredlogs ; extra == 'all'
Requires-Dist: chardet ==5.1.0 ; extra == 'all'
Requires-Dist: clickhouse-connect ; extra == 'all'
Requires-Dist: msgpack ; extra == 'all'
Requires-Dist: jsonschema ; extra == 'all'
Requires-Dist: optimum ; extra == 'all'
Requires-Dist: weaviate-client ; extra == 'all'
Requires-Dist: fschat ; extra == 'all'
Requires-Dist: pympler ; extra == 'all'
Requires-Dist: tenacity <=8.3.0 ; extra == 'all'
Requires-Dist: pydantic >=2.6.0 ; extra == 'all'
Requires-Dist: psycopg2 ; extra == 'all'
Requires-Dist: markdown ; extra == 'all'
Requires-Dist: SQLAlchemy <2.0.29,>=2.0.25 ; extra == 'all'
Requires-Dist: uvicorn ; extra == 'all'
Requires-Dist: colorama ==0.4.6 ; extra == 'all'
Requires-Dist: duckdb-engine ; extra == 'all'
Requires-Dist: pandas ==2.0.3 ; extra == 'all'
Requires-Dist: torchvision ==0.17.1 ; extra == 'all'
Requires-Dist: autoawq ; extra == 'all'
Requires-Dist: shortuuid ; extra == 'all'
Requires-Dist: python-docx ; extra == 'all'
Requires-Dist: pypdf ; extra == 'all'
Requires-Dist: schedule ; extra == 'all'
Requires-Dist: cachetools ; extra == 'all'
Requires-Dist: sqlparse ==0.4.4 ; extra == 'all'
Requires-Dist: opentelemetry-exporter-otlp ; extra == 'all'
Requires-Dist: openai ; extra == 'all'
Requires-Dist: chardet ; extra == 'all'
Requires-Dist: auto-gpt-plugin-template ; extra == 'all'
Requires-Dist: cpm-kernels ; extra == 'all'
Requires-Dist: spacy >=3.7 ; extra == 'all'
Requires-Dist: typeguard ; extra == 'all'
Requires-Dist: importlib-resources ==5.12.0 ; extra == 'all'
Requires-Dist: tokenizers >=0.14 ; extra == 'all'
Requires-Dist: numpy <2.0.0,>=1.21.0 ; extra == 'all'
Requires-Dist: graphviz ; extra == 'all'
Requires-Dist: click ; extra == 'all'
Requires-Dist: chromadb >=0.4.22 ; extra == 'all'
Requires-Dist: pyspark ; extra == 'all'
Requires-Dist: tiktoken ; extra == 'all'
Requires-Dist: seaborn ; extra == 'all'
Requires-Dist: transformers >=4.34.0 ; extra == 'all'
Requires-Dist: rich ; extra == 'all'
Requires-Dist: typing-inspect ; extra == 'all'
Requires-Dist: fastapi >=0.100.0 ; extra == 'all'
Requires-Dist: pyhive ; extra == 'all'
Requires-Dist: python-dotenv ==1.0.0 ; extra == 'all'
Requires-Dist: termcolor ; extra == 'all'
Requires-Dist: vertica-python ; extra == 'all'
Requires-Dist: bs4 ; extra == 'all'
Requires-Dist: bitsandbytes ; extra == 'all'
Requires-Dist: aiofiles ; extra == 'all'
Requires-Dist: pydoris <2.0.0,>=1.0.2 ; extra == 'all'
Requires-Dist: zhipuai ; extra == 'all'
Requires-Dist: duckdb ; extra == 'all'
Requires-Dist: opentelemetry-sdk ; extra == 'all'
Requires-Dist: thrift ; extra == 'all'
Requires-Dist: gpt4all ; extra == 'all'
Requires-Dist: auto-gptq ; extra == 'all'
Requires-Dist: opentelemetry-api ; extra == 'all'
Requires-Dist: mysqlclient ==2.1.0 ; extra == 'all'
Requires-Dist: openpyxl ==3.1.2 ; extra == 'all'
Requires-Dist: alembic ==1.12.0 ; extra == 'all'
Requires-Dist: neo4j ; extra == 'all'
Requires-Dist: GitPython ; extra == 'all'
Requires-Dist: python-pptx ; extra == 'all'
Requires-Dist: accelerate >=0.20.3 ; extra == 'all'
Provides-Extra: bitsandbytes
Requires-Dist: bitsandbytes ; extra == 'bitsandbytes'
Provides-Extra: cache
Requires-Dist: rocksdict ; extra == 'cache'
Provides-Extra: cli
Requires-Dist: colorama ==0.4.6 ; extra == 'cli'
Requires-Dist: python-dotenv ==1.0.0 ; extra == 'cli'
Requires-Dist: cachetools ; extra == 'cli'
Requires-Dist: typeguard ; extra == 'cli'
Requires-Dist: aiohttp ==3.8.4 ; extra == 'cli'
Requires-Dist: tomlkit ; extra == 'cli'
Requires-Dist: tenacity <=8.3.0 ; extra == 'cli'
Requires-Dist: importlib-resources ==5.12.0 ; extra == 'cli'
Requires-Dist: pydantic >=2.6.0 ; extra == 'cli'
Requires-Dist: psutil ==5.9.4 ; extra == 'cli'
Requires-Dist: chardet ==5.1.0 ; extra == 'cli'
Requires-Dist: prettytable ; extra == 'cli'
Requires-Dist: rich ; extra == 'cli'
Requires-Dist: snowflake-id ; extra == 'cli'
Requires-Dist: httpx ; extra == 'cli'
Requires-Dist: typing-inspect ; extra == 'cli'
Requires-Dist: fastapi >=0.100.0 ; extra == 'cli'
Requires-Dist: click ; extra == 'cli'
Provides-Extra: client
Requires-Dist: python-dotenv ==1.0.0 ; extra == 'client'
Requires-Dist: cachetools ; extra == 'client'
Requires-Dist: typeguard ; extra == 'client'
Requires-Dist: aiohttp ==3.8.4 ; extra == 'client'
Requires-Dist: tenacity <=8.3.0 ; extra == 'client'
Requires-Dist: importlib-resources ==5.12.0 ; extra == 'client'
Requires-Dist: pydantic >=2.6.0 ; extra == 'client'
Requires-Dist: chardet ==5.1.0 ; extra == 'client'
Requires-Dist: snowflake-id ; extra == 'client'
Requires-Dist: httpx ; extra == 'client'
Requires-Dist: typing-inspect ; extra == 'client'
Requires-Dist: fastapi >=0.100.0 ; extra == 'client'
Provides-Extra: core
Requires-Dist: python-dotenv ==1.0.0 ; extra == 'core'
Requires-Dist: cachetools ; extra == 'core'
Requires-Dist: typeguard ; extra == 'core'
Requires-Dist: aiohttp ==3.8.4 ; extra == 'core'
Requires-Dist: importlib-resources ==5.12.0 ; extra == 'core'
Requires-Dist: pydantic >=2.6.0 ; extra == 'core'
Requires-Dist: chardet ==5.1.0 ; extra == 'core'
Requires-Dist: snowflake-id ; extra == 'core'
Requires-Dist: typing-inspect ; extra == 'core'
Provides-Extra: datasource
Requires-Dist: pymysql ; extra == 'datasource'
Provides-Extra: datasource_all
Requires-Dist: pyspark ; extra == 'datasource_all'
Requires-Dist: vertica-python ; extra == 'datasource_all'
Requires-Dist: mysqlclient ==2.1.0 ; extra == 'datasource_all'
Requires-Dist: thrift-sasl ; extra == 'datasource_all'
Requires-Dist: thrift ; extra == 'datasource_all'
Requires-Dist: neo4j ; extra == 'datasource_all'
Requires-Dist: pymysql ; extra == 'datasource_all'
Requires-Dist: psycopg2 ; extra == 'datasource_all'
Requires-Dist: clickhouse-connect ; extra == 'datasource_all'
Requires-Dist: pymssql ; extra == 'datasource_all'
Requires-Dist: pyhive ; extra == 'datasource_all'
Requires-Dist: pydoris <2.0.0,>=1.0.2 ; extra == 'datasource_all'
Provides-Extra: default
Requires-Dist: python-multipart ; extra == 'default'
Requires-Dist: schedule ; extra == 'default'
Requires-Dist: cachetools ; extra == 'default'
Requires-Dist: sqlparse ==0.4.4 ; extra == 'default'
Requires-Dist: tomlkit ; extra == 'default'
Requires-Dist: coloredlogs ; extra == 'default'
Requires-Dist: opentelemetry-exporter-otlp ; extra == 'default'
Requires-Dist: jinja2 ; extra == 'default'
Requires-Dist: chardet ==5.1.0 ; extra == 'default'
Requires-Dist: zhipuai ; extra == 'default'
Requires-Dist: chardet ; extra == 'default'
Requires-Dist: msgpack ; extra == 'default'
Requires-Dist: duckdb ; extra == 'default'
Requires-Dist: auto-gpt-plugin-template ; extra == 'default'
Requires-Dist: jsonschema ; extra == 'default'
Requires-Dist: cpm-kernels ; extra == 'default'
Requires-Dist: optimum ; extra == 'default'
Requires-Dist: opentelemetry-sdk ; extra == 'default'
Requires-Dist: rocksdict ; extra == 'default'
Requires-Dist: autoawq ; extra == 'default'
Requires-Dist: spacy >=3.7 ; extra == 'default'
Requires-Dist: xlrd ==2.0.1 ; extra == 'default'
Requires-Dist: typeguard ; extra == 'default'
Requires-Dist: torchaudio ==2.2.1 ; extra == 'default'
Requires-Dist: importlib-resources ==5.12.0 ; extra == 'default'
Requires-Dist: tokenizers >=0.14 ; extra == 'default'
Requires-Dist: pymysql ; extra == 'default'
Requires-Dist: psutil ==5.9.4 ; extra == 'default'
Requires-Dist: numpy <2.0.0,>=1.21.0 ; extra == 'default'
Requires-Dist: sentencepiece ; extra == 'default'
Requires-Dist: fschat ; extra == 'default'
Requires-Dist: sentence-transformers ; extra == 'default'
Requires-Dist: auto-gptq ; extra == 'default'
Requires-Dist: graphviz ; extra == 'default'
Requires-Dist: httpx ; extra == 'default'
Requires-Dist: python-pptx ; extra == 'default'
Requires-Dist: pympler ; extra == 'default'
Requires-Dist: opentelemetry-api ; extra == 'default'
Requires-Dist: click ; extra == 'default'
Requires-Dist: chromadb >=0.4.22 ; extra == 'default'
Requires-Dist: aiohttp ==3.8.4 ; extra == 'default'
Requires-Dist: tenacity <=8.3.0 ; extra == 'default'
Requires-Dist: seaborn ; extra == 'default'
Requires-Dist: pydantic >=2.6.0 ; extra == 'default'
Requires-Dist: dashscope ; extra == 'default'
Requires-Dist: alembic ==1.12.0 ; extra == 'default'
Requires-Dist: openpyxl ==3.1.2 ; extra == 'default'
Requires-Dist: transformers >=4.34.0 ; extra == 'default'
Requires-Dist: prettytable ; extra == 'default'
Requires-Dist: gTTS ==2.3.1 ; extra == 'default'
Requires-Dist: markdown ; extra == 'default'
Requires-Dist: snowflake-id ; extra == 'default'
Requires-Dist: rich ; extra == 'default'
Requires-Dist: fastapi >=0.100.0 ; extra == 'default'
Requires-Dist: typing-inspect ; extra == 'default'
Requires-Dist: SQLAlchemy <2.0.29,>=2.0.25 ; extra == 'default'
Requires-Dist: uvicorn ; extra == 'default'
Requires-Dist: colorama ==0.4.6 ; extra == 'default'
Requires-Dist: torch ==2.2.1 ; extra == 'default'
Requires-Dist: python-dotenv ==1.0.0 ; extra == 'default'
Requires-Dist: termcolor ; extra == 'default'
Requires-Dist: duckdb-engine ; extra == 'default'
Requires-Dist: pandas ==2.0.3 ; extra == 'default'
Requires-Dist: GitPython ; extra == 'default'
Requires-Dist: ollama ; extra == 'default'
Requires-Dist: torchvision ==0.17.1 ; extra == 'default'
Requires-Dist: bs4 ; extra == 'default'
Requires-Dist: bitsandbytes ; extra == 'default'
Requires-Dist: aiofiles ; extra == 'default'
Requires-Dist: shortuuid ; extra == 'default'
Requires-Dist: python-docx ; extra == 'default'
Requires-Dist: accelerate >=0.20.3 ; extra == 'default'
Requires-Dist: pypdf ; extra == 'default'
Provides-Extra: framework
Requires-Dist: schedule ; extra == 'framework'
Requires-Dist: cachetools ; extra == 'framework'
Requires-Dist: sqlparse ==0.4.4 ; extra == 'framework'
Requires-Dist: tomlkit ; extra == 'framework'
Requires-Dist: coloredlogs ; extra == 'framework'
Requires-Dist: jinja2 ; extra == 'framework'
Requires-Dist: chardet ==5.1.0 ; extra == 'framework'
Requires-Dist: msgpack ; extra == 'framework'
Requires-Dist: duckdb ; extra == 'framework'
Requires-Dist: auto-gpt-plugin-template ; extra == 'framework'
Requires-Dist: jsonschema ; extra == 'framework'
Requires-Dist: xlrd ==2.0.1 ; extra == 'framework'
Requires-Dist: typeguard ; extra == 'framework'
Requires-Dist: importlib-resources ==5.12.0 ; extra == 'framework'
Requires-Dist: pymysql ; extra == 'framework'
Requires-Dist: psutil ==5.9.4 ; extra == 'framework'
Requires-Dist: numpy <2.0.0,>=1.21.0 ; extra == 'framework'
Requires-Dist: fschat ; extra == 'framework'
Requires-Dist: graphviz ; extra == 'framework'
Requires-Dist: httpx ; extra == 'framework'
Requires-Dist: pympler ; extra == 'framework'
Requires-Dist: click ; extra == 'framework'
Requires-Dist: aiohttp ==3.8.4 ; extra == 'framework'
Requires-Dist: tenacity <=8.3.0 ; extra == 'framework'
Requires-Dist: seaborn ; extra == 'framework'
Requires-Dist: pydantic >=2.6.0 ; extra == 'framework'
Requires-Dist: openpyxl ==3.1.2 ; extra == 'framework'
Requires-Dist: alembic ==1.12.0 ; extra == 'framework'
Requires-Dist: transformers >=4.34.0 ; extra == 'framework'
Requires-Dist: prettytable ; extra == 'framework'
Requires-Dist: gTTS ==2.3.1 ; extra == 'framework'
Requires-Dist: rich ; extra == 'framework'
Requires-Dist: snowflake-id ; extra == 'framework'
Requires-Dist: typing-inspect ; extra == 'framework'
Requires-Dist: fastapi >=0.100.0 ; extra == 'framework'
Requires-Dist: SQLAlchemy <2.0.29,>=2.0.25 ; extra == 'framework'
Requires-Dist: uvicorn ; extra == 'framework'
Requires-Dist: colorama ==0.4.6 ; extra == 'framework'
Requires-Dist: python-dotenv ==1.0.0 ; extra == 'framework'
Requires-Dist: termcolor ; extra == 'framework'
Requires-Dist: duckdb-engine ; extra == 'framework'
Requires-Dist: pandas ==2.0.3 ; extra == 'framework'
Requires-Dist: GitPython ; extra == 'framework'
Requires-Dist: aiofiles ; extra == 'framework'
Requires-Dist: shortuuid ; extra == 'framework'
Provides-Extra: gpt4all
Requires-Dist: gpt4all ; extra == 'gpt4all'
Provides-Extra: llama_cpp
Requires-Dist: llama-cpp-python ; extra == 'llama_cpp'
Provides-Extra: observability
Requires-Dist: opentelemetry-sdk ; extra == 'observability'
Requires-Dist: opentelemetry-api ; extra == 'observability'
Requires-Dist: opentelemetry-exporter-otlp ; extra == 'observability'
Provides-Extra: openai
Requires-Dist: python-multipart ; extra == 'openai'
Requires-Dist: schedule ; extra == 'openai'
Requires-Dist: cachetools ; extra == 'openai'
Requires-Dist: sqlparse ==0.4.4 ; extra == 'openai'
Requires-Dist: opentelemetry-exporter-otlp ; extra == 'openai'
Requires-Dist: tomlkit ; extra == 'openai'
Requires-Dist: coloredlogs ; extra == 'openai'
Requires-Dist: jinja2 ; extra == 'openai'
Requires-Dist: openai ; extra == 'openai'
Requires-Dist: chardet ==5.1.0 ; extra == 'openai'
Requires-Dist: msgpack ; extra == 'openai'
Requires-Dist: duckdb ; extra == 'openai'
Requires-Dist: opentelemetry-sdk ; extra == 'openai'
Requires-Dist: auto-gpt-plugin-template ; extra == 'openai'
Requires-Dist: jsonschema ; extra == 'openai'
Requires-Dist: spacy >=3.7 ; extra == 'openai'
Requires-Dist: xlrd ==2.0.1 ; extra == 'openai'
Requires-Dist: typeguard ; extra == 'openai'
Requires-Dist: importlib-resources ==5.12.0 ; extra == 'openai'
Requires-Dist: pymysql ; extra == 'openai'
Requires-Dist: psutil ==5.9.4 ; extra == 'openai'
Requires-Dist: numpy <2.0.0,>=1.21.0 ; extra == 'openai'
Requires-Dist: sentence-transformers ; extra == 'openai'
Requires-Dist: fschat ; extra == 'openai'
Requires-Dist: graphviz ; extra == 'openai'
Requires-Dist: httpx ; extra == 'openai'
Requires-Dist: opentelemetry-api ; extra == 'openai'
Requires-Dist: pympler ; extra == 'openai'
Requires-Dist: python-pptx ; extra == 'openai'
Requires-Dist: click ; extra == 'openai'
Requires-Dist: chromadb >=0.4.22 ; extra == 'openai'
Requires-Dist: tiktoken ; extra == 'openai'
Requires-Dist: aiohttp ==3.8.4 ; extra == 'openai'
Requires-Dist: tenacity <=8.3.0 ; extra == 'openai'
Requires-Dist: seaborn ; extra == 'openai'
Requires-Dist: pydantic >=2.6.0 ; extra == 'openai'
Requires-Dist: openpyxl ==3.1.2 ; extra == 'openai'
Requires-Dist: alembic ==1.12.0 ; extra == 'openai'
Requires-Dist: transformers >=4.34.0 ; extra == 'openai'
Requires-Dist: prettytable ; extra == 'openai'
Requires-Dist: gTTS ==2.3.1 ; extra == 'openai'
Requires-Dist: markdown ; extra == 'openai'
Requires-Dist: snowflake-id ; extra == 'openai'
Requires-Dist: rich ; extra == 'openai'
Requires-Dist: typing-inspect ; extra == 'openai'
Requires-Dist: fastapi >=0.100.0 ; extra == 'openai'
Requires-Dist: SQLAlchemy <2.0.29,>=2.0.25 ; extra == 'openai'
Requires-Dist: uvicorn ; extra == 'openai'
Requires-Dist: colorama ==0.4.6 ; extra == 'openai'
Requires-Dist: python-dotenv ==1.0.0 ; extra == 'openai'
Requires-Dist: termcolor ; extra == 'openai'
Requires-Dist: duckdb-engine ; extra == 'openai'
Requires-Dist: pandas ==2.0.3 ; extra == 'openai'
Requires-Dist: GitPython ; extra == 'openai'
Requires-Dist: bs4 ; extra == 'openai'
Requires-Dist: aiofiles ; extra == 'openai'
Requires-Dist: shortuuid ; extra == 'openai'
Requires-Dist: python-docx ; extra == 'openai'
Requires-Dist: pypdf ; extra == 'openai'
Provides-Extra: quantization
Requires-Dist: optimum ; extra == 'quantization'
Requires-Dist: bitsandbytes ; extra == 'quantization'
Requires-Dist: auto-gptq ; extra == 'quantization'
Requires-Dist: autoawq ; extra == 'quantization'
Requires-Dist: cpm-kernels ; extra == 'quantization'
Provides-Extra: rag
Requires-Dist: chromadb >=0.4.22 ; extra == 'rag'
Requires-Dist: spacy >=3.7 ; extra == 'rag'
Requires-Dist: python-multipart ; extra == 'rag'
Requires-Dist: bs4 ; extra == 'rag'
Requires-Dist: sentence-transformers ; extra == 'rag'
Requires-Dist: markdown ; extra == 'rag'
Requires-Dist: python-pptx ; extra == 'rag'
Requires-Dist: python-docx ; extra == 'rag'
Requires-Dist: pypdf ; extra == 'rag'
Provides-Extra: simple_framework
Requires-Dist: schedule ; extra == 'simple_framework'
Requires-Dist: cachetools ; extra == 'simple_framework'
Requires-Dist: sqlparse ==0.4.4 ; extra == 'simple_framework'
Requires-Dist: tomlkit ; extra == 'simple_framework'
Requires-Dist: jinja2 ; extra == 'simple_framework'
Requires-Dist: chardet ==5.1.0 ; extra == 'simple_framework'
Requires-Dist: msgpack ; extra == 'simple_framework'
Requires-Dist: duckdb ; extra == 'simple_framework'
Requires-Dist: typeguard ; extra == 'simple_framework'
Requires-Dist: importlib-resources ==5.12.0 ; extra == 'simple_framework'
Requires-Dist: psutil ==5.9.4 ; extra == 'simple_framework'
Requires-Dist: numpy <2.0.0,>=1.21.0 ; extra == 'simple_framework'
Requires-Dist: fschat ; extra == 'simple_framework'
Requires-Dist: httpx ; extra == 'simple_framework'
Requires-Dist: pympler ; extra == 'simple_framework'
Requires-Dist: click ; extra == 'simple_framework'
Requires-Dist: aiohttp ==3.8.4 ; extra == 'simple_framework'
Requires-Dist: tenacity <=8.3.0 ; extra == 'simple_framework'
Requires-Dist: pydantic >=2.6.0 ; extra == 'simple_framework'
Requires-Dist: prettytable ; extra == 'simple_framework'
Requires-Dist: rich ; extra == 'simple_framework'
Requires-Dist: snowflake-id ; extra == 'simple_framework'
Requires-Dist: typing-inspect ; extra == 'simple_framework'
Requires-Dist: fastapi >=0.100.0 ; extra == 'simple_framework'
Requires-Dist: SQLAlchemy <2.0.29,>=2.0.25 ; extra == 'simple_framework'
Requires-Dist: uvicorn ; extra == 'simple_framework'
Requires-Dist: colorama ==0.4.6 ; extra == 'simple_framework'
Requires-Dist: python-dotenv ==1.0.0 ; extra == 'simple_framework'
Requires-Dist: termcolor ; extra == 'simple_framework'
Requires-Dist: duckdb-engine ; extra == 'simple_framework'
Requires-Dist: pandas ==2.0.3 ; extra == 'simple_framework'
Requires-Dist: shortuuid ; extra == 'simple_framework'
Provides-Extra: torch
Requires-Dist: torch ==2.2.1 ; extra == 'torch'
Requires-Dist: torchaudio ==2.2.1 ; extra == 'torch'
Requires-Dist: torchvision ==0.17.1 ; extra == 'torch'
Provides-Extra: torch_cpu
Requires-Dist: torch ==2.2.1 ; extra == 'torch_cpu'
Requires-Dist: torchaudio ==2.2.1 ; extra == 'torch_cpu'
Requires-Dist: torchvision ==0.17.1 ; extra == 'torch_cpu'
Provides-Extra: torch_cuda
Requires-Dist: torch ==2.2.1 ; extra == 'torch_cuda'
Requires-Dist: torchaudio ==2.2.1 ; extra == 'torch_cuda'
Requires-Dist: torchvision ==0.17.1 ; extra == 'torch_cuda'
Provides-Extra: vllm
Requires-Dist: vllm ; extra == 'vllm'
Provides-Extra: vstore
Requires-Dist: chromadb >=0.4.22 ; extra == 'vstore'
Provides-Extra: vstore_all
Requires-Dist: chromadb >=0.4.22 ; extra == 'vstore_all'
Requires-Dist: weaviate-client ; extra == 'vstore_all'
Requires-Dist: pymilvus ; extra == 'vstore_all'
Provides-Extra: vstore_milvus
Requires-Dist: chromadb >=0.4.22 ; extra == 'vstore_milvus'
Requires-Dist: pymilvus ; extra == 'vstore_milvus'
Provides-Extra: vstore_weaviate
Requires-Dist: chromadb >=0.4.22 ; extra == 'vstore_weaviate'
Requires-Dist: weaviate-client ; extra == 'vstore_weaviate'
